{
    "BestScore": 94,
    "BestScoreUserName": "Clap",
    "RankUserDataList": [
        {
            "userName": "Clap",
            "userScore": 94
        },
        {
            "userName": "Rolling",
            "userScore": 26
        },
        {
            "userName": "BabyCat",
            "userScore": 15
        },
        {
            "userName": "Happy",
            "userScore": 8
        },
        {
            "userName": "Journey",
            "userScore": 4
        },
        {
            "userName": "Hello",
            "userScore": 1
        },
        {
            "userName": "-",
            "userScore": 0
        },
        {
            "userName": "-",
            "userScore": 0
        },
        {
            "userName": "-",
            "userScore": 0
        },
        {
            "userName": "-",
            "userScore": 0
        }
    ],
    "SettingColorDataList": []
}